ironclad/__init__.py
ironclad/__init__.pyi
ironclad/_utils.py
ironclad/arg_validation.py
ironclad/arg_validation.pyi
ironclad/multimethod.py
ironclad/multimethod.pyi
ironclad/py.typed
ironclad/type_repr.py
ironclad/type_repr.pyi
ironclad/types.py
ironclad/types.pyi
ironclad/predicates/__init__.py
ironclad/predicates/__init__.pyi
ironclad/predicates/predicate.py
ironclad/predicates/predicate.pyi
ironclad/predicates/predicates.py
ironclad/predicates/predicates.pyi
ironclad-0.1.0.dist-info/METADATA
ironclad-0.1.0.dist-info/WHEEL
ironclad-0.1.0.dist-info/licenses/LICENSE.md
ironclad-0.1.0.dist-info/RECORD
