Metadata-Version: 2.4
Name: ironclad
Version: 0.1.0
Summary: Runtime contracts and predicate-based validation for Python.
Project-URL: Homepage, https://github.com/zentiph/ironclad
Project-URL: Repository, https://github.com/zentiph/ironclad
Project-URL: Issues, https://github.com/zentiph/ironclad/issues
Project-URL: Documentation, https://zentiph.github.io/ironclad
Project-URL: Changelog, https://github.com/zentiph/ironclad/blob/main/CHANGELOG.md
Author-email: "Zentiph (Gavin Borne)" <zentiphdev@gmail.com>
License: Copyright 2025-present Zentiph
License-File: LICENSE.md
Keywords: contracts,predicates,runtime,types,validation
Classifier: Development Status :: 4 - Beta
Classifier: Intended Audience :: Developers
Classifier: License :: OSI Approved :: MIT License
Classifier: Programming Language :: Python
Classifier: Programming Language :: Python :: 3
Classifier: Programming Language :: Python :: 3 :: Only
Classifier: Programming Language :: Python :: 3.11
Classifier: Programming Language :: Python :: 3.12
Classifier: Programming Language :: Python :: 3.13
Classifier: Topic :: Software Development :: Libraries
Classifier: Typing :: Typed
Requires-Python: >=3.11
Provides-Extra: dev
Requires-Dist: build; extra == 'dev'
Requires-Dist: mkdocs; extra == 'dev'
Requires-Dist: mkdocs-material; extra == 'dev'
Requires-Dist: mkdocstrings[python]; extra == 'dev'
Requires-Dist: mypy; extra == 'dev'
Requires-Dist: pygments; extra == 'dev'
Requires-Dist: pymdown-extensions; extra == 'dev'
Requires-Dist: pytest; extra == 'dev'
Requires-Dist: ruff; extra == 'dev'
Requires-Dist: twine; extra == 'dev'
